barfy/__init__.py
barfy/chitrapat/SplashConfig.py
barfy/chitrapat/SplashScreen_Dark.py
barfy/chitrapat/SplashScreen_Growing.py
barfy/chitrapat/SplashScreen_Load.py
barfy/chitrapat/SplashScreen_Transparent.py
barfy/chitrapat/TextBarfy.py
barfy/chitrapat/__init__.py
barfy/chitrapat/ext/SplashScreen_DarkEx.py
barfy/chitrapat/ext/SplashScreen_GrowingEx.py
barfy/chitrapat/ext/SplashScreen_LoadEx.py
barfy/chitrapat/ext/SplashScreen_TransparentEx.py
barfy/chitrapat/ext/__init__.py
test/TestingWindow.py
test/__init__.py
test/main.py
barfy-1.0.1.dist-info/LICENSE.txt
barfy-1.0.1.dist-info/METADATA
barfy-1.0.1.dist-info/WHEEL
barfy-1.0.1.dist-info/top_level.txt
barfy-1.0.1.dist-info/RECORD
