Metadata-Version: 2.1
Name: barfy
Version: 1.0.1
Summary: It is python package which will be used for splash screen in PyQt5 built projects and application.
Home-page: https://github.com/ChitreshPratap/barfy/blob/main/README.md
Author: AbhilashChitresh
Author-email: UNKNOWN
License: https://github.com/ChitreshPratap/barfy/blob/main/LICENSE.txt
Platform: UNKNOWN
